Workbook
Name Slicer_Product_Name: #N/A

Sheet Dashboard
E1: Shaheen Electronics, Ltd
E3: Monthly Report (Dec 25 - Jan 26)
E5: Detailed Analysis of Products & Provinces by Revenue, Quantity, and Shares | Q5: Net Analysis (Total Revenue, Quantity, and Shares)
E8: Punjab | H8: =VLOOKUP('Pivot Data'!A4,'Pivot Data'!A9:G18,5,0) -> 104500 | K8: =VLOOKUP('Pivot Data'!A4,'Pivot Data'!A22:G31,5,0) -> 110 | N8: =VLOOKUP('Pivot Data'!A4,'Pivot Data'!A35:G44,5,0) -> 0.3264095 | Q8: =HLOOKUP(E8,'Pivot Data'!A9:G18,10,0) -> 3601000 | T8: =HLOOKUP(E8,'Pivot Data'!A22:G31,10,0) -> 189 | W8: =HLOOKUP(E8,'Pivot Data'!A35:G44,10,0) -> 0.24809417
E10: Sindh | H10: =VLOOKUP('Pivot Data'!A4,'Pivot Data'!A9:G18,6,0) -> 0 | K10: =VLOOKUP('Pivot Data'!A4,'Pivot Data'!A22:G31,6,0) -> 0 | N10: =VLOOKUP('Pivot Data'!A4,'Pivot Data'!A35:G44,6,0) -> 0 | Q10: =HLOOKUP(E10,'Pivot Data'!A9:G18,10,0) -> 4592500 | T10: =HLOOKUP(E10,'Pivot Data'!A22:G31,10,0) -> 97 | W10: =HLOOKUP(E10,'Pivot Data'!A35:G44,10,0) -> 0.31640446
E12: Balochistan | H12: =VLOOKUP('Pivot Data'!A4,'Pivot Data'!A9:G18,2,0) -> 114000 | K12: =VLOOKUP('Pivot Data'!A4,'Pivot Data'!A22:G31,2,0) -> 120 | N12: =VLOOKUP('Pivot Data'!A4,'Pivot Data'!A35:G44,2,0) -> 0.35608309 | Q12: =HLOOKUP(E12,'Pivot Data'!A9:G18,10,0) -> 3231500 | T12: =HLOOKUP(E12,'Pivot Data'!A22:G31,10,0) -> 172 | W12: =HLOOKUP(E12,'Pivot Data'!A35:G44,10,0) -> 0.22263713
E14: Khyber | H14: =VLOOKUP('Pivot Data'!A4,'Pivot Data'!A9:G18,4,0) -> 57000 | K14: =VLOOKUP('Pivot Data'!A4,'Pivot Data'!A22:G31,4,0) -> 60 | N14: =VLOOKUP('Pivot Data'!A4,'Pivot Data'!A35:G44,4,0) -> 0.17804154 | Q14: =HLOOKUP(E14,'Pivot Data'!A9:G18,10,0) -> 1453000 | T14: =HLOOKUP(E14,'Pivot Data'!A22:G31,10,0) -> 87 | W14: =HLOOKUP(E14,'Pivot Data'!A35:G44,10,0) -> 0.10010576
E16: Gilgit Baltistan | H16: =VLOOKUP('Pivot Data'!A4,'Pivot Data'!A9:G18,3,0) -> 44650 | K16: =VLOOKUP('Pivot Data'!A4,'Pivot Data'!A22:G31,3,0) -> 47 | N16: =VLOOKUP('Pivot Data'!A4,'Pivot Data'!A35:G44,3,0) -> 0.13946588 | Q16: =HLOOKUP(E16,'Pivot Data'!A9:G18,10,0) -> 1636650 | T16: =HLOOKUP(E16,'Pivot Data'!A22:G31,10,0) -> 68 | W16: =HLOOKUP(E16,'Pivot Data'!A35:G44,10,0) -> 0.11275849
E18: Totals | H18: =SUM(H8:I16) -> 320150 | K18: =SUM(K8:L16) -> 337 | N18: =SUM(N8:O16) -> 1 | Q18: =SUM(Q8:R16) -> 14514650 | T18: =SUM(T8:U16) -> 613 | W18: =SUM(W8:X16) -> 1
B62: Provinces | C62: Revenue
B63: Punjab | C63: =H8 -> 104500
B64: Sindh | C64: =H10 -> 0
B65: Balochistan | C65: =H12 -> 114000
B66: Khyber | C66: =H14 -> 57000
B67: Gilgit | C67: =H16 -> 44650
B69: Provinces | C69: Quantity
B70: Punjab | C70: =K8 -> 110
B71: Sindh | C71: =K10 -> 0
B72: Balochistan | C72: =K12 -> 120
B73: Khyber | C73: =K14 -> 60
B74: Gilgit | C74: =K16 -> 47
B76: Provinces | C76: Shares
B77: Punjab | C77: =N8 -> 0.3264095
B78: Sindh | C78: =N10 -> 0
B79: Balochistan | C79: =N12 -> 0.35608309
B80: Khyber | C80: =N14 -> 0.17804154
B81: Gilgit | C81: =N16 -> 0.13946588

Sheet Pivot Data
A1: Province | B1: (ALL)
A3: Row Labels | B3: Sum of Total Price
A4: SanDisk 32 GB USB | B4: 320150
A5: Grand Total | B5: 320150
A8: Sum of Total Price | B8: Column Labels
A9: Row Labels | B9: Balochistan | C9: Gilgit Baltistan | D9: Khyber | E9: Punjab | F9: Sindh | G9: Grand Total
A10: DDR5 16 GB RAM | B10: 667000 | D10: 348000 | E10: 1218000 | F10: 1624000 | G10: 3857000
A11: Dell Laptop | B11: 1034000 | C11: 752000 | D11: 658000 | E11: 470000 | G11: 2914000
A12: HP Laptop | B12: 504000 | C12: 84000 | F12: 1008000 | G12: 1596000
A13: Lenovo Laptop | B13: 76500 | C13: 612000 | E13: 229500 | F13: 1294500 | G13: 2212500
A14: Samsung 32 inch LED | C14: 144000 | D14: 72000 | E14: 252000 | F14: 180000 | G14: 648000
A15: Samsung Phone | B15: 836000 | E15: 532000 | F15: 380000 | G15: 1748000
A16: SanDisk 32 GB USB | B16: 114000 | C16: 44650 | D16: 57000 | E16: 104500 | G16: 320150
A17: Vivo Phone | D17: 318000 | E17: 795000 | F17: 106000 | G17: 1219000
A18: Grand Total | B18: 3231500 | C18: 1636650 | D18: 1453000 | E18: 3601000 | F18: 4592500 | G18: 14514650
A21: Sum of Quantity | B21: Province
A22: Product Name | B22: Balochistan | C22: Gilgit Baltistan | D22: Khyber | E22: Punjab | F22: Sindh | G22: Grand Total
A23: DDR5 16 GB RAM | B23: 23 | D23: 12 | E23: 42 | F23: 56 | G23: 133
A24: Dell Laptop | B24: 11 | C24: 8 | D24: 7 | E24: 5 | G24: 31
A25: HP Laptop | B25: 6 | C25: 1 | F25: 12 | G25: 19
A26: Lenovo Laptop | B26: 1 | C26: 8 | E26: 3 | F26: 17 | G26: 29
A27: Samsung 32 inch LED | C27: 4 | D27: 2 | E27: 7 | F27: 5 | G27: 18
A28: Samsung Phone | B28: 11 | E28: 7 | F28: 5 | G28: 23
A29: SanDisk 32 GB USB | B29: 120 | C29: 47 | D29: 60 | E29: 110 | G29: 337
A30: Vivo Phone | D30: 6 | E30: 15 | F30: 2 | G30: 23
A31: Grand Total | B31: 172 | C31: 68 | D31: 87 | E31: 189 | F31: 97 | G31: 613
A34: Sum of Total Price | B34: Province
A35: Product Name | B35: Balochistan | C35: Gilgit Baltistan | D35: Khyber | E35: Punjab | F35: Sindh | G35: Grand Total
A36: DDR5 16 GB RAM | B36: 0.17293233 | C36: 0 | D36: 0.090225564 | E36: 0.31578947 | F36: 0.42105263 | G36: 1
A37: Dell Laptop | B37: 0.35483871 | C37: 0.25806452 | D37: 0.22580645 | E37: 0.16129032 | F37: 0 | G37: 1
A38: HP Laptop | B38: 0.31578947 | C38: 0.052631579 | D38: 0 | E38: 0 | F38: 0.63157895 | G38: 1
A39: Lenovo Laptop | B39: 0.034576271 | C39: 0.27661017 | D39: 0 | E39: 0.10372881 | F39: 0.58508475 | G39: 1
A40: Samsung 32 inch LED | B40: 0 | C40: 0.22222222 | D40: 0.11111111 | E40: 0.38888889 | F40: 0.27777778 | G40: 1
A41: Samsung Phone | B41: 0.47826087 | C41: 0 | D41: 0 | E41: 0.30434783 | F41: 0.2173913 | G41: 1
A42: SanDisk 32 GB USB | B42: 0.35608309 | C42: 0.13946588 | D42: 0.17804154 | E42: 0.3264095 | F42: 0 | G42: 1
A43: Vivo Phone | B43: 0 | C43: 0 | D43: 0.26086957 | E43: 0.65217391 | F43: 0.086956522 | G43: 1
A44: Grand Total | B44: 0.22263713 | C44: 0.11275849 | D44: 0.10010576 | E44: 0.24809417 | F44: 0.31640446 | G44: 1

Sheet Database
A1: Date | B1: Time | C1: Product Name | D1: Order ID | E1: Province | F1: City | G1: Quantity | H1: Unit Price | I1: Total Price | J1: Date Completion | K1: Delivered By | L1: Payment Type
A2: 45993 | B2: 0.53888889 | C2: Lenovo Laptop | D2: TX324853 | E2: Balochistan | F2: Quetta | G2: 1 | H2: 76500 | I2: =G2*H2 -> 76500 | J2: 45996 | K2: Usman Hanif | L2: Cash
A3: 45993 | B3: 0.61458333 | C3: Samsung Phone | D3: TX324854 | E3: Punjab | F3: Muzaffargarh | G3: 2 | H3: 76000 | I3: =G3*H3 -> 152000 | J3: 45995 | K3: Ali Sheikh | L3: Jazzcash
A4: 45993 | B4: 0.62222222 | C4: SanDisk 32 GB USB | D4: TX324855 | E4: Punjab | F4: Vehari | G4: 70 | H4: 950 | I4: =G4*H4 -> 66500 | J4: 45997 | K4: Imran Ali | L4: Bank
A5: 45993 | B5: 0.64861111 | C5: DDR5 16 GB RAM | D5: TX324856 | E5: Sindh | F5: Hyderabad | G5: 45 | H5: 29000 | I5: =G5*H5 -> 1305000 | J5: 45996 | K5: Imran Saeed | L5: Bank
A6: 45993 | B6: 0.65138889 | C6: Dell Laptop | D6: TX324857 | E6: Balochistan | F6: Sibbi | G6: 1 | H6: 94000 | I6: =G6*H6 -> 94000 | J6: 45998 | K6: Rana Bilawal | L6: Easypaisa
A7: 45993 | B7: 0.80763889 | C7: Samsung 32 inch LED | D7: TX324858 | E7: Punjab | F7: Murree | G7: 2 | H7: 36000 | I7: =G7*H7 -> 72000 | J7: 45994 | K7: Ali Sheikh | L7: Cash
A8: 45995 | B8: 0.44027778 | C8: Lenovo Laptop | D8: TX324859 | E8: Gilgit Baltistan | F8: Gilgit | G8: 3 | H8: 76500 | I8: =G8*H8 -> 229500 | J8: 45999 | K8: Usman Hanif | L8: Cash
A9: 45995 | B9: 0.49722222 | C9: DDR5 16 GB RAM | D9: TX324860 | E9: Punjab | F9: Faisalabad | G9: 6 | H9: 29000 | I9: =G9*H9 -> 174000 | J9: 45998 | K9: Ali Sheikh | L9: Bank
A10: 45995 | B10: 0.65 | C10: Samsung Phone | D10: TX324861 | E10: Sindh | F10: Karachi | G10: 5 | H10: 76000 | I10: =G10*H10 -> 380000 | J10: 45999 | K10: Imran Ali | L10: Easypaisa
A11: 45996 | B11: 0.75486111 | C11: Dell Laptop | D11: TX324862 | E11: Punjab | F11: Chitral | G11: 2 | H11: 94000 | I11: =G11*H11 -> 188000 | J11: 46000 | K11: Rana Bilawal | L11: Cash
A12: 45996 | B12: 0.83541667 | C12: SanDisk 32 GB USB | D12: TX324863 | E12: Balochistan | F12: Qallat | G12: 23 | H12: 950 | I12: =G12*H12 -> 21850 | J12: 46001 | K12: Usman Hanif | L12: Jazzcash
A13: 45997 | B13: 0.39722222 | C13: Samsung 32 inch LED | D13: TX324864 | E13: Khyber | F13: Pishawar | G13: 2 | H13: 36000 | I13: =G13*H13 -> 72000 | J13: 46000 | K13: Imran Saeed | L13: Bank
... A54: 46037 | B54: 0.65 | C54: SanDisk 32 GB USB | D54: TX324905 | E54: Balochistan | F54: Port Qasim | G54: 12 | H54: 950 | I54: =G54*H54 -> 11400 | J54: 46041 | K54: Rana Bilawal | L54: Easypaisa
